restapidocs/ApiDefinition.py
restapidocs/ApiMethodSpec.py
restapidocs/ApiObjectSchema.py
restapidocs/ApiParameter.py
restapidocs/ApiRequestBody.py
restapidocs/ApiResponseSpec.py
restapidocs/ApiSchema.py
restapidocs/ApiSchemaProperty.py
restapidocs/HTTP.py
restapidocs/Responses.py
restapidocs/SecurityDefinition.py
restapidocs/__init__.py
restapidocs-0.0.1a0.dist-info/METADATA
restapidocs-0.0.1a0.dist-info/WHEEL
restapidocs-0.0.1a0.dist-info/top_level.txt
restapidocs-0.0.1a0.dist-info/RECORD
