Metadata-Version: 2.1
Name: restapidocs
Version: 0.0.1a0
Summary: Decorator for Flask end point to add OpenAPI documentation to end point using classes that generate a YAML documentation
Home-page: https://github.com/jordsti/restapidocs
Maintainer: Jordsti
Maintainer-email: jord52@gmail.com
License: MIT
Platform: UNKNOWN
Classifier: Environment :: Web Environment
Classifier: Intended Audience :: Developers
Classifier: Programming Language :: Python
Classifier: Programming Language :: Python :: 3.7
Requires-Dist: flasgger (>=0.9.0)
